Arduino_Master/Arduino_Master.py
Arduino_Master/__init__.py
Arduino_Master-3.dist-info/LICENSE.txt
Arduino_Master-3.dist-info/METADATA
Arduino_Master-3.dist-info/WHEEL
Arduino_Master-3.dist-info/top_level.txt
Arduino_Master-3.dist-info/RECORD
