Metadata-Version: 2.1
Name: Arduino-Master
Version: 3
Summary: Data Science enabled Data extraction and control library for Arduino with easy Data Visualizations !.
Home-page: https://github.com/SayadPervez/Arduino_Master
Author: Sayad Pervez
Author-email: pervez2504@gmail.com
License: UNKNOWN
Platform: UNKNOWN
Classifier: Programming Language :: Python :: 3
Classifier: License :: OSI Approved :: MIT License
Classifier: Operating System :: OS Independent
